idli/__init__.py
idli/connection.py
idli/errors.py
idli/helpers.py
idli/internal.py
idli/model_methods.py
idli/sql_factory.py
idli-0.1.0.dist-info/METADATA
idli-0.1.0.dist-info/WHEEL
idli-0.1.0.dist-info/top_level.txt
idli-0.1.0.dist-info/RECORD
