Metadata-Version: 2.4
Name: idli
Version: 0.1.0
Summary: Nag-free PostgreSQL ORM
Project-URL: Homepage, https://github.com/kdqed/zaturn
Project-URL: Issues, https://github.com/kdqed/zaturn/issues
Requires-Python: >=3.13
Requires-Dist: psycopg-pool>=3.2.8
Requires-Dist: psycopg[binary]>=3.2.13
